pysimplefunctioins/__init__.py
pysimplefunctioins/example.py
pysimplefunctions-0.0.1.dist-info/METADATA
pysimplefunctions-0.0.1.dist-info/WHEEL
pysimplefunctions-0.0.1.dist-info/top_level.txt
pysimplefunctions-0.0.1.dist-info/RECORD
